iicd_workshop_2024/__init__.py
iicd_workshop_2024/gene_model.py
iicd_workshop_2024/inference.py
iicd_workshop_2024/neural_network.py
iicd_workshop_2024-0.1.0.dist-info/LICENSE
iicd_workshop_2024-0.1.0.dist-info/METADATA
iicd_workshop_2024-0.1.0.dist-info/WHEEL
iicd_workshop_2024-0.1.0.dist-info/RECORD
