Metadata-Version: 2.1
Name: iicd_workshop_2024
Version: 0.1.0
Summary: Code accompanying the iicd workshop 2024
Home-page: https://github.com/anazaret/iicd-workshop-2024
Author: Achille Nazaret
Author-email: achille.nazaret@gmail.com
Requires-Python: >=3.9,<4.0
Classifier: Programming Language :: Python :: 3
Classifier: Programming Language :: Python :: 3.9
Classifier: Programming Language :: Python :: 3.10
Classifier: Programming Language :: Python :: 3.11
Classifier: Programming Language :: Python :: 3.12
Project-URL: Documentation, https://anazaret.github.io/iicd-workshop-2024/
Project-URL: Repository, https://github.com/anazaret/iicd-workshop-2024
